Qidong/Test.py
Qidong/__init__.py
Qidong-0.1.0.dist-info/LICENSE
Qidong-0.1.0.dist-info/METADATA
Qidong-0.1.0.dist-info/WHEEL
Qidong-0.1.0.dist-info/top_level.txt
Qidong-0.1.0.dist-info/RECORD
