Metadata-Version: 2.1
Name: Qidong
Version: 0.1.0
Summary: Qidong's study
Home-page: UNKNOWN
Author: Qidong
Author-email: dong_liuqi@163.com
License: MIT Licence
Keywords: pip,pathtool,timetool,magetool,mage
Platform: any
